aiogram_album/__init__.py
aiogram_album/album_message.py
aiogram_album/base_message.py
aiogram_album/count_check_middleware.py
aiogram_album/lock_middleware.py
aiogram_album/methods/__init__.py
aiogram_album/methods/copy_messages.py
aiogram_album/methods/delete_messages.py
aiogram_album/methods/forward_messages.py
aiogram_album/methods/message_id.py
aiogram_album/no_check_count_middleware.py
aiogram_album/pyrogram_album/__init__.py
aiogram_album/pyrogram_album/message.py
aiogram_album/pyrogram_album/middleware.py
aiogram_album/pyrogram_album/utls.py
aiogram_album/ttl_cache_middleware.py
aiogram_album-0.0.3b0.dist-info/LICENSE
aiogram_album-0.0.3b0.dist-info/METADATA
aiogram_album-0.0.3b0.dist-info/WHEEL
aiogram_album-0.0.3b0.dist-info/RECORD
