Metadata-Version: 2.1
Name: aiogram_album
Version: 0.0.3b0
Summary: 😎
Author: RootShinobi
Author-email: 111008396+RootShinobi@users.noreply.github.com
Requires-Python: >=3.8,<4.0
Classifier: Programming Language :: Python :: 3
Classifier: Programming Language :: Python :: 3.8
Classifier: Programming Language :: Python :: 3.9
Classifier: Programming Language :: Python :: 3.10
Classifier: Programming Language :: Python :: 3.11
Classifier: Programming Language :: Python :: 3.12
Requires-Dist: aiogram (>=3.0.0,<4.0.0)
